{
  "_comment": "鸣潮常驻池配置 - 基于 XutheringWavesUID 数据校验",
  "character": {
    "id": "standard_char",
    "name": "常规唤取（角色）",
    "5star": ["鉴心", "卡卡罗", "维里奈", "凌阳", "安可"],
    "4star_characters": ["渊武", "白芷", "釉瑚", "炽霞", "散华", "秋水", "桃祈", "丹瑾", "秧秧", "灯灯", "莫特斐", "卜灵"],
    "4star_weapons": [
      "不归孤军", "东落", "今州守望", "凋亡频移", "凌空",
      "华彩乐段", "叙别的罗曼史", "呼啸重音", "大海的馈赠",
      "奇幻变奏", "奔雷", "容赦的沉思录", "尘云旋臂",
      "异响空灵", "异度", "心之锚", "悖论喷流",
      "无眠烈火", "曜光", "核熔星盘", "永夜长明",
      "永续坍缩", "清音", "渊海回声", "瞬斩刀-18型",
      "穿击枪-26型", "纹秋", "翼锋", "虚饰的华尔兹",
      "行进序曲", "袍泽之固", "西升", "酩酊的英雄志",
      "重破刃-41型", "金掌", "金穹", "钢影拳-21丁型",
      "阳焰", "风流的寓言诗", "飞景", "飞逝",
      "骇行", "鸣动仪-25型"
    ]
  },
  "weapon": {
    "id": "standard_weapon",
    "name": "常规唤取（武器）",
    "5star": ["苍鳞千嶂", "赫奕流明", "死与舞", "诸方玄枢", "掣傀之手", "时和岁稔", "裁春", "林间的咏叹调", "浩境粼光", "千古洑流", "停驻之烟", "擎渊怒涛", "漪澜浮录", "源能机锋", "镭射切变", "相位涟漪", "脉冲协臂", "玻色星仪"],
    "4star_weapons": [
      "不归孤军", "东落", "今州守望", "凋亡频移", "凌空",
      "华彩乐段", "叙别的罗曼史", "呼啸重音", "大海的馈赠",
      "奇幻变奏", "奔雷", "容赦的沉思录", "尘云旋臂",
      "异响空灵", "异度", "心之锚", "悖论喷流",
      "无眠烈火", "曜光", "核熔星盘", "永夜长明",
      "永续坍缩", "清音", "渊海回声", "瞬斩刀-18型",
      "穿击枪-26型", "纹秋", "翼锋", "虚饰的华尔兹",
      "行进序曲", "袍泽之固", "西升", "酩酊的英雄志",
      "重破刃-41型", "金掌", "金穹", "钢影拳-21丁型",
      "阳焰", "风流的寓言诗", "飞景", "飞逝",
      "骇行", "鸣动仪-25型"
    ],
    "4star_characters": ["渊武", "白芷", "釉瑚", "炽霞", "散华", "秋水", "桃祈", "丹瑾", "秧秧", "灯灯", "莫特斐", "卜灵"]
  }
}
